CHANGES.rst
LICENSE
MANIFEST.in
NOTICE
README.rst
setup.py
doc/Makefile
doc/changes.rst
doc/conf.py
doc/configuration.rst
doc/history.rst
doc/index.rst
doc/installation.rst
doc/make.bat
doc/quickstart.rst
doc/regions.rst
doc/signals.rst
doc/transitions.rst
doc/images/add-data-center-asset-form.png
doc/images/add_licence.png
doc/images/add_support.png
doc/images/asset_add_device.png
doc/images/asset_add_part.png
doc/images/bulk-1.png
doc/images/bulk-2.png
doc/images/edit-device-status.png
doc/images/edit-device.png
doc/images/overview.png
doc/images/reports_multilanguage.png
doc/images/user_page.png
doc/images/regions/add-new-region.png
doc/images/regions/assign-region-to-asset.png
doc/images/regions/assign-region-to-user.png
doc/theme/bs/layout.html
doc/theme/bs/theme.conf
doc/theme/bs/static/bs.css
doc/theme/bs/static/jquery.js
doc/theme/bs/static/restyle.js
doc/theme/bs/static/bootstrap/css/bootstrap-responsive.css
doc/theme/bs/static/bootstrap/css/bootstrap-responsive.min.css
doc/theme/bs/static/bootstrap/css/bootstrap.css
doc/theme/bs/static/bootstrap/css/bootstrap.min.css
doc/theme/bs/static/bootstrap/img/glyphicons-halflings-white.png
doc/theme/bs/static/bootstrap/img/glyphicons-halflings.png
doc/theme/bs/static/bootstrap/js/bootstrap.js
doc/theme/bs/static/bootstrap/js/bootstrap.min.js
src/ralph_assets/__init__.py
src/ralph_assets/admin.py
src/ralph_assets/api.py
src/ralph_assets/api_pricing.py
src/ralph_assets/api_ralph.py
src/ralph_assets/api_scrooge.py
src/ralph_assets/app.py
src/ralph_assets/exceptions.py
src/ralph_assets/forms.py
src/ralph_assets/forms_import.py
src/ralph_assets/forms_support.py
src/ralph_assets/forms_transitions.py
src/ralph_assets/forms_utils.py
src/ralph_assets/menu.py
src/ralph_assets/models.py
src/ralph_assets/models_assets.py
src/ralph_assets/models_dc_assets.py
src/ralph_assets/models_signals.py
src/ralph_assets/models_support.py
src/ralph_assets/models_transition.py
src/ralph_assets/models_util.py
src/ralph_assets/others.py
src/ralph_assets.egg-info/PKG-INFO
src/ralph_assets.egg-info/SOURCES.txt
src/ralph_assets.egg-info/dependency_links.txt
src/ralph_assets.egg-info/entry_points.txt
src/ralph_assets.egg-info/not-zip-safe
src/ralph_assets.egg-info/pbr.json
src/ralph_assets.egg-info/requires.txt
src/ralph_assets.egg-info/top_level.txt
